LICENSE
MANIFEST.in
README.rst
setup.py
django_easy_contact_setup.egg-info/PKG-INFO
django_easy_contact_setup.egg-info/SOURCES.txt
django_easy_contact_setup.egg-info/dependency_links.txt
django_easy_contact_setup.egg-info/not-zip-safe
django_easy_contact_setup.egg-info/requires.txt
django_easy_contact_setup.egg-info/top_level.txt
easy_contact_setup/__init__.py
easy_contact_setup/__init__.pyc
easy_contact_setup/admin.py
easy_contact_setup/admin.pyc
easy_contact_setup/forms.py
easy_contact_setup/forms.pyc
easy_contact_setup/models.py
easy_contact_setup/models.pyc
easy_contact_setup/version.py
easy_contact_setup/version.pyc
easy_contact_setup/locale/de/LC_MESSAGES/django.mo
easy_contact_setup/locale/de/LC_MESSAGES/django.po
easy_contact_setup/locale/en/LC_MESSAGES/django.mo
easy_contact_setup/locale/en/LC_MESSAGES/django.po