Metadata-Version: 1.1
Name: django-easy-contact-setup
Version: 0.3.8
Summary: Admin set up for django-easy-contact
Home-page: https://bitbucket.org/catapela/django-easy-contact-setup
Author: Andreas Fritz, digital.elements.li
Author-email: easy-contact-setup@bitzeit.eu
License: BSD
Download-URL: https://pypi.python.org/pypi/django-easy-contact-setup
Keywords: django mail configuration setup mailform
Platform: UNKNOWN
Classifier: Development Status :: 4 - Beta
Classifier: Framework :: Django
Classifier: License :: OSI Approved :: BSD License
Classifier: Operating System :: OS Independent
Classifier: Programming Language :: Python
Classifier: Environment :: Console
Classifier: Natural Language :: English
Classifier: Natural Language :: German
Classifier: Intended Audience :: Developers
Classifier: Intended Audience :: Information Technology
Classifier: Topic :: Internet
Classifier: Topic :: Utilities
